sutro/__init__.py
sutro/cli.py
sutro/common.py
sutro/interfaces.py
sutro/sdk.py
sutro/templates/classification.py
sutro/templates/embed.py
sutro/templates/evals.py
sutro/validation.py
sutro-0.1.52.dist-info/WHEEL
sutro-0.1.52.dist-info/entry_points.txt
sutro-0.1.52.dist-info/METADATA
sutro-0.1.52.dist-info/RECORD
