Metadata-Version: 2.4
Name: sutro
Version: 0.1.52
Summary: Sutro Python SDK
License-Expression: Apache-2.0
Requires-Dist: numpy>=2.1.1,<3.0.0
Requires-Dist: requests>=2.32.3,<3.0.0
Requires-Dist: pandas>=2.2.3,<3.0.0
Requires-Dist: polars>=1.33.0,<=1.34.0
Requires-Dist: click>=8.1.7,<9.0.0
Requires-Dist: colorama>=0.4.4,<1.0.0
Requires-Dist: yaspin>=3.2.0,<4.0.0
Requires-Dist: tqdm>=4.67.1,<5.0.0
Requires-Dist: pydantic>=2.11.4,<3.0.0
Requires-Dist: pyarrow>=21.0.0,<22.0.0
Requires-Dist: tabulate>=0.9.0,<1.0.0
Requires-Python: >=3.10
Project-URL: Documentation, https://docs.sutro.sh
Project-URL: Homepage, https://sutro.sh
